{"data":[[{"gpsDataId":27422,"dateTime":"2015-12-12T06:21:25","latitude":41.1,"latitudeDirection":"N","longitude":87.1,"longitudeDirection":"W","altitude":10.0,"legSpeed":null,"legHeading":350.0,"legTimeSecs":null,"legLength":null},{"sessionPersistId":27421,"dateTime":"2015-12-12T06:21:25","startDateTime":"2015-12-12T06:21:25","endDateTime":"2015-12-12T06:21:25","sessionName":"test 4","sessionDescription":"test Session Description"}],[{"gpsDataId":27423,"dateTime":"2015-12-12T06:21:25","latitude":41.0,"latitudeDirection":"N","longitude":87.0,"longitudeDirection":"W","altitude":11.0,"legSpeed":null,"legHeading":355.0,"legTimeSecs":null,"legLength":null},{"sessionPersistId":27421,"dateTime":"2015-12-12T06:21:25","startDateTime":"2015-12-12T06:21:25","endDateTime":"2015-12-12T06:21:25","sessionName":"test 4","sessionDescription":"test Session Description"}]]}